libkarel/__init__.py
libkarel/kareltest.py
libkarel/libkarel.py
libkarel-1.1.2.dist-info/licenses/LICENSE
libkarel-1.1.2.dist-info/METADATA
libkarel-1.1.2.dist-info/WHEEL
libkarel-1.1.2.dist-info/top_level.txt
libkarel-1.1.2.dist-info/RECORD
