Metadata-Version: 2.4
Name: libkarel
Version: 1.1.2
Summary: Utilities for validating karel.js/ReKarel test cases
Author-email: omegaUp <lhchavez@omegaup.org>
License: MIT
Classifier: Programming Language :: Python :: 3
Classifier: License :: OSI Approved :: MIT License
Classifier: Operating System :: OS Independent
Requires-Python: >=3.6
License-File: LICENSE
Dynamic: license-file
